{"image_id": "012s93RNzvJt", "url": "http://mm.dimu.org/image/012s93RNzvJt?dimension=400x400", "photographer": "0", "id": 37396, "artifact_id": "011013949428", "unique_id": "011013949428", "type": "Photograph", "title": "Flerbostadshus under uppf\u00f6rande, Uppsala 1938", "place_of_production": "Sverige, Uppland, Uppsala, Uppsala, Uppsala", "published": "2014-04-30T01:50:47.667Z", "updated": "2021-07-03T08:15:52.182Z", "year_from": 1938, "year_to": 1938, "producer": "Sagerholm, Axel", "motif": "Flerbostadshus under uppf\u00f6rande, Uppsala 1938", "coordinate_id": null, "owner_id": 3, "collection_id": 3, "name": "Upplandsmuseets samlingar", "uuid": "c02bf63b753140bc88c183f2e5ec3d4c", "owner_name": "Upplandsmuseet"}