{"image_id": "022uK2ywhro2", "url": "http://mm.dimu.org/image/022uK2ywhro2?dimension=400x400", "photographer": "0", "id": 3388, "artifact_id": "011014738880", "unique_id": "011014738880", "type": "Photograph", "title": "Linjerna R\u00e5da - L\u00e5ngflon. Postutv\u00e4xling i Ambj\u00f6rby.", "place_of_production": "Sverige, V\u00e4rmland, V\u00e4rmland, Torsby, Ambj\u00f6rby L\u00e5ngflon, V\u00e4rmland Ny Norra socken V\u00e4rmlands l\u00e4n Sverige, V\u00e4rmland, V\u00e4rmland, Hagfors, R\u00e5da", "published": "2014-08-14T19:28:57.916Z", "updated": "2021-05-31T12:33:21.484Z", "year_from": 1930, "year_to": 1939, "producer": null, "motif": "Linjerna R\u00e5da - L\u00e5ngflon. Postutv\u00e4xling i Ambj\u00f6rby.", "coordinate_id": 146, "owner_id": 6, "collection_id": 6, "name": "Primus", "uuid": "373f8bbbedd048ef9031203fba082d7a", "owner_name": "Postmuseum"}