{"image_id": "022ynU6xCrHi", "url": "http://mm.dimu.org/image/022ynU6xCrHi?dimension=400x400", "photographer": "0", "id": 2977, "artifact_id": "021016964327", "unique_id": "021016964327", "type": "Photograph", "title": "\"Tore Alinder st\u00e5r med foten p\u00e5 en sten i skogsbacken\", troligen Hedesunda, G\u00e4strikland 1930", "place_of_production": "Sverige, G\u00e4strikland, G\u00e4vleborg, G\u00e4vle, Hedesunda, Hedesunda", "published": "2017-04-11T06:04:09.113Z", "updated": "2022-07-07T04:35:22.183Z", "year_from": 1930, "year_to": 1930, "producer": "Alinder, John", "motif": "\"Tore Alinder st\u00e5r med foten p\u00e5 en sten i skogsbacken\", troligen Hedesunda, G\u00e4strikland 1930", "coordinate_id": null, "owner_id": 3, "collection_id": 3, "name": "Upplandsmuseets samlingar", "uuid": "c02bf63b753140bc88c183f2e5ec3d4c", "owner_name": "Upplandsmuseet"}