{"image_id": "022ykz8Tqp2Z", "url": "http://mm.dimu.org/image/022ykz8Tqp2Z?dimension=400x400", "photographer": "0", "id": 35393, "artifact_id": "021017161866", "unique_id": "021017161866", "type": "Photograph", "title": null, "place_of_production": "Sverige, V\u00e4sterg\u00f6tland, V\u00e4stra G\u00f6taland, Vara, Barne, Ryda, Rylanda, Skaraborg", "published": "2017-08-17T18:18:42.273Z", "updated": "2019-08-20T04:04:23.828Z", "year_from": 1937, "year_to": 1937, "producer": "AB Flygtrafik", "motif": "", "coordinate_id": null, "owner_id": 9, "collection_id": 9, "name": "VGM Foto", "uuid": "2815a7357dad42b0ac1b35d7a9a91845", "owner_name": "V\u00e4sterg\u00f6tlands museum"}