{"image_id": "02347Tgma7Gk", "url": "http://mm.dimu.org/image/02347Tgma7Gk?dimension=400x400", "photographer": "0", "id": 1242, "artifact_id": "021018353344", "unique_id": "021018353344", "type": "Photograph", "title": "Text i fotoalbum: \"16. juli 1938 startade hfk (h\u00f6gre fortifikationskurs) en l\u00e5ngresa med inlandsbanan fr\u00e5n \u00d6stersund till Gellivare. Erhardt \u00e4r myggh\u00e4rdig.\"", "place_of_production": "Sverige, Lappland, Norrbotten, G\u00e4llivare, Dundret", "published": "2019-06-08T05:15:29.753Z", "updated": "2019-06-08T05:15:29.753Z", "year_from": 1938, "year_to": 1938, "producer": "Ok\u00e4nd", "motif": "Text i fotoalbum: \"16. juli 1938 startade hfk (h\u00f6gre fortifikationskurs) en l\u00e5ngresa med inlandsbanan fr\u00e5n \u00d6stersund till Gellivare. Erhardt \u00e4r myggh\u00e4rdig.\"", "coordinate_id": null, "owner_id": 25, "collection_id": 28, "name": "Arm\u00e9museums arkiv", "uuid": "98ebabdbd6684681b7fc52742a9540b1", "owner_name": "Arm\u00e9museum"}