{"image_id": "032sA2rGtJaC", "url": "http://mm.dimu.org/image/032sA2rGtJaC?dimension=400x400", "photographer": "Larsson (fotograf F 2)", "id": 55040, "artifact_id": "011014092326", "unique_id": "011014092326", "type": "Photograph", "title": "Lysbojar p\u00e5 vattnet vid F 2 Roslagens flygflottilj, 1936", "place_of_production": "Sverige, Uppland, H\u00e4gern\u00e4s", "published": "2014-06-03T03:01:40.189Z", "updated": "2019-05-07T03:41:27.377Z", "year_from": 1936, "year_to": 1936, "producer": "Larsson (fotograf F 2)", "motif": "Lysbojar p\u00e5 vattnet vid F 2 Roslagens flygflottilj, 1936", "coordinate_id": null, "owner_id": 17, "collection_id": 17, "name": "Flygvapenmuseums arkivsamling", "uuid": "310b50e8e6c16c72e050a8c024255fef", "owner_name": "Flygvapenmuseum"}