{"image_id": "032sBXqRkdBe", "url": "http://mm.dimu.org/image/032sBXqRkdBe?dimension=400x400", "photographer": "0", "id": 39963, "artifact_id": "011014481315", "unique_id": "011014481315", "type": "Photograph", "title": "Text till bilden:\"Grinner\u00f6ds Folkskolan\".", "place_of_production": "Sverige, V\u00e4stra G\u00f6taland, Uddevalla, Grinner\u00f6d, Grinner\u00f6d", "published": "2014-08-13T08:56:01.393Z", "updated": "2019-07-12T04:34:11.417Z", "year_from": 1939, "year_to": 1939, "producer": "Henriksson, Karl Gustaf Henrik", "motif": "Text till bilden:\"Grinner\u00f6ds Folkskolan\".", "coordinate_id": null, "owner_id": 4, "collection_id": 4, "name": "S14UM Fotosamlingen", "uuid": "43ea206803274bc0a251d8f1216350e4", "owner_name": "Bohusl\u00e4ns museum"}