{"image_id": "032wY1ch7xxx", "url": "http://mm.dimu.org/image/032wY1ch7xxx?dimension=400x400", "photographer": "0", "id": 13440, "artifact_id": "021016133592", "unique_id": "021016133592", "type": "Photograph", "title": "Olaus Petriskolan, klassrumsinteri\u00f6r, 27 pojkar med l\u00e4rare G\u00f6sta Sw\u00e4rd.\nKlass 6A, sal 29.", "place_of_production": "Sverige, N\u00e4rke, \u00d6rebro, \u00d6rebro, \u00d6rebro, \u00d6rebro_", "published": "2016-01-14T05:04:17.915Z", "updated": "2021-12-15T03:53:03.287Z", "year_from": 1939, "year_to": 1939, "producer": "Lindskog, Samuel", "motif": "Olaus Petriskolan, klassrumsinteri\u00f6r, 27 pojkar med l\u00e4rare G\u00f6sta Sw\u00e4rd.\rKlass 6A, sal 29.", "coordinate_id": 3, "owner_id": 11, "collection_id": 11, "name": "Foto", "uuid": "3576ceb3989341a2bd0eab31e7060c5a", "owner_name": "\u00d6rebro l\u00e4ns museum"}