{"image_id": "0331xy7FoXWQ", "url": "http://mm.dimu.org/image/0331xy7FoXWQ?dimension=400x400", "photographer": "0", "id": 26048, "artifact_id": "021018039139", "unique_id": "021018039139", "type": "Photograph", "title": "Trollh\u00e4ttan station.", "place_of_production": "Sverige, V\u00e4sterg\u00f6tland, V\u00e4stra G\u00f6taland, Trollh\u00e4ttan, Trollh\u00e4ttan", "published": "2018-12-22T07:38:42.798Z", "updated": "2021-02-13T04:46:22.641Z", "year_from": 1930, "year_to": 1939, "producer": "T-foto,", "motif": "Trollh\u00e4ttan station.", "coordinate_id": null, "owner_id": 10, "collection_id": 10, "name": "J\u00e4rnv\u00e4gsmuseets foton", "uuid": "aa94bdd4f74f4db49067c2e25c6d23d5", "owner_name": "J\u00e4rnv\u00e4gsmuseet"}