{"image_id": "0331yTYJgfDR", "url": "http://mm.dimu.org/image/0331yTYJgfDR?dimension=400x400", "photographer": "0", "id": 72733, "artifact_id": "021018103603", "unique_id": "021018103603", "type": "Photograph", "title": "Motala stationsomr\u00e5de.", "place_of_production": "Sverige, \u00d6sterg\u00f6tland, \u00d6sterg\u00f6tland, Motala, Motala, Motala C", "published": "2018-12-29T07:34:04.828Z", "updated": "2021-02-27T07:23:40.851Z", "year_from": 1930, "year_to": 1930, "producer": "Fotograf ok\u00e4nd, ", "motif": "Motala stationsomr\u00e5de.", "coordinate_id": null, "owner_id": 10, "collection_id": 10, "name": "J\u00e4rnv\u00e4gsmuseets foton", "uuid": "aa94bdd4f74f4db49067c2e25c6d23d5", "owner_name": "J\u00e4rnv\u00e4gsmuseet"}