{"image_id": "0331wU89uXnG", "url": "http://mm.dimu.org/image/0331wU89uXnG?dimension=400x400", "photographer": "0", "id": 25042, "artifact_id": "021017837789", "unique_id": "021017837789", "type": "Photograph", "title": "Flygfoto \u00f6ver stationen", "place_of_production": "Sverige, V\u00e4rmland, S\u00e4ffle, V\u00e4rmlandsbro", "published": "2018-06-19T06:02:55.744Z", "updated": "2021-01-14T04:31:28.533Z", "year_from": 1935, "year_to": 1935, "producer": "AB Flygtrafik, Dals L\u00e5nged", "motif": "Flygfoto \u00f6ver stationen", "coordinate_id": null, "owner_id": 10, "collection_id": 10, "name": "J\u00e4rnv\u00e4gsmuseets foton", "uuid": "aa94bdd4f74f4db49067c2e25c6d23d5", "owner_name": "J\u00e4rnv\u00e4gsmuseet"}